winnie/__init__.py
winnie/byteops.py
winnie/connection.py
winnie/constants.py
winnie/formatting.py
winnie/listops.py
winnie/resourceMask.py
winnie/sessionStatus.py
winnie/verification.py
winnie-0.0.6.dist-info/LICENSE
winnie-0.0.6.dist-info/METADATA
winnie-0.0.6.dist-info/WHEEL
winnie-0.0.6.dist-info/top_level.txt
winnie-0.0.6.dist-info/RECORD
