Metadata-Version: 2.1
Name: winnie
Version: 0.0.6
Summary: CCP library
Home-page: https://github.com/HWRacing/winnie
Author: HWRacing
Author-email: fs60@hw.ac.uk
Project-URL: Bug Tracker, https://github.com/HWRacing/winnie/issues
Classifier: Programming Language :: Python :: 3
Classifier: Programming Language :: Python :: 3 :: Only
Classifier: Programming Language :: Python :: 3.8
Classifier: Programming Language :: Python :: 3.9
Classifier: Programming Language :: Python :: 3.10
Classifier: Programming Language :: Python :: 3.11
Classifier: License :: OSI Approved :: MIT License
Requires-Python: >=3.8
License-File: LICENSE
Provides-Extra: testing
Requires-Dist: pytest (>=7.0) ; extra == 'testing'
Requires-Dist: tox (>=4.4.0) ; extra == 'testing'
Requires-Dist: mypy (>=1.0.0) ; extra == 'testing'
